phoenixpegasus.py
phoenixpegasus-0.0.1.dist-info/LICENSE
phoenixpegasus-0.0.1.dist-info/METADATA
phoenixpegasus-0.0.1.dist-info/WHEEL
phoenixpegasus-0.0.1.dist-info/top_level.txt
phoenixpegasus-0.0.1.dist-info/RECORD
