Metadata-Version: 2.1
Name: phoenixpegasus
Version: 0.0.1
Summary: Access to the PHOENIX PEGASUS grid by Dr. Sarah Peacock
Home-page: UNKNOWN
Author: Malia Barker
License: UNKNOWN
Platform: UNKNOWN
Classifier: Programming Language :: Python :: 3
Classifier: License :: OSI Approved :: MIT License
Classifier: Operating System :: OS Independent
Requires-Python: >=3.6
